aioregistry/__init__.py
aioregistry/__main__.py
aioregistry/auth.py
aioregistry/cli.py
aioregistry/client.py
aioregistry/exceptions.py
aioregistry/models.py
aioregistry/parsing.py
aioregistry/py.typed
aioregistry/utils.py
aioregistry-0.7.2.dist-info/LICENSE
aioregistry-0.7.2.dist-info/METADATA
aioregistry-0.7.2.dist-info/WHEEL
aioregistry-0.7.2.dist-info/entry_points.txt
aioregistry-0.7.2.dist-info/top_level.txt
aioregistry-0.7.2.dist-info/RECORD
