Metadata-Version: 2.1
Name: aioregistry
Version: 0.7.2
Summary: Python library for interacting with container image registries
Home-page: http://github.com/msg555/aioregistry
Author: Mark Gordon
Author-email: msg555@gmail.com
Classifier: Programming Language :: Python :: 3
Classifier: License :: OSI Approved :: BSD License
Classifier: Operating System :: OS Independent
Requires-Python: >=3.8
License-File: LICENSE
Requires-Dist: aiohttp <4,>=3.8
Requires-Dist: pydantic <3,>=1.8
Provides-Extra: tqdm
Requires-Dist: tqdm <5,>=4.20.0 ; extra == 'tqdm'
